MANIFEST.in
README.rst
setup.py
party/__init__.py
party/aql.py
party/exceptions.py
party/party.py
party/party_aql.py
party/party_config.py
party/party_request.py
party/sample.py
party.egg-info/PKG-INFO
party.egg-info/SOURCES.txt
party.egg-info/dependency_links.txt
party.egg-info/requires.txt
party.egg-info/top_level.txt