Metadata-Version: 1.0
Name: party
Version: 1.7.3
Summary: Lightweight Python client to the Artifactory API.
Home-page: http://pypi.python.org/pypi/Party/
Author: Ted Sheibar
Author-email: tsheibar@gmail.com
License: LICENSE.txt
Platform: UNKNOWN
